<?xml version="1.0"?>
<!DOCTYPE hibernate-mapping PUBLIC "-//Hibernate/Hibernate Mapping DTD 3.0//EN"
"http://hibernate.sourceforge.net/hibernate-mapping-3.0.dtd">
<!-- Generated 2014-7-20 10:18:15 by Hibernate Tools 3.4.0.CR1 -->
<hibernate-mapping>
    <class name="com.realty.base.model.LandPoss" table="land_poss" schema="dbo" catalog="realty">
        <id name="landpossId" type="int">
            <column name="landposs_id" />
            <generator class="assigned" />
        </id>
        <property name="landpossName" type="string">
            <column name="landposs_name" />
        </property>
    </class>
</hibernate-mapping>
